coarsage.cpython-312-darwin.so
graphs.cpython-312-darwin.so
pdf_conformal.cpython-312-darwin.so
pdf_discrete.cpython-312-darwin.so
pdf_group.cpython-312-darwin.so
pdf_set.cpython-312-darwin.so
prob_regr_unit.cpython-312-darwin.so
prob_regressor.cpython-312-darwin.so
structure_dt.cpython-312-darwin.so
structure_dt_multi.cpython-312-darwin.so
structure_gb.cpython-312-darwin.so
structure_gb_multi.cpython-312-darwin.so
structureboost/__init__.py
structureboost/coarsage.c
structureboost/graphs.c
structureboost/pdf_conformal.c
structureboost/pdf_discrete.c
structureboost/pdf_group.c
structureboost/pdf_set.c
structureboost/prob_regr_unit.c
structureboost/prob_regressor.c
structureboost/structure_dt.c
structureboost/structure_dt_multi.c
structureboost/structure_gb.c
structureboost/structure_gb_multi.c
structureboost/utils.py
structureboost/tests/__init__.py
structureboost/tests/test_basics.py
structureboost/tests/test_coarsage_1.py
structureboost/tests/test_dt.py
structureboost/tests/test_gb.py
structureboost/tests/test_graphs.py
structureboost/tests/test_multi_1.py
structureboost/tests/test_pdfgroup1.py
structureboost/tests/test_predict_options.py
structureboost/tests/test_prob_reg_1.py
structureboost/tests/test_shap.py
structureboost-0.7.0.dist-info/licenses/LICENSE
structureboost-0.7.0.dist-info/METADATA
structureboost-0.7.0.dist-info/WHEEL
structureboost-0.7.0.dist-info/top_level.txt
structureboost-0.7.0.dist-info/RECORD
