Metadata-Version: 2.4
Name: structureboost
Version: 0.7.0
Summary: Gradient Boosting and Probabilistic Regression with categorical structure
Author-email: Brian Lucena <brian@numeristical.com>
License-Expression: MIT
Classifier: Programming Language :: Python :: 3
Classifier: Operating System :: OS Independent
Requires-Python: >=3.8
License-File: LICENSE
Requires-Dist: pandas>=1.3
Requires-Dist: numpy>=1.23.5
Requires-Dist: scipy>=1.6
Requires-Dist: matplotlib>=1.0
Requires-Dist: joblib>=0.14.1
Requires-Dist: ml_insights>=1.0.5
Provides-Extra: dev
Requires-Dist: Cython>=3.1.0b1; extra == "dev"
Requires-Dist: build; extra == "dev"
Requires-Dist: setuptools; extra == "dev"
Dynamic: license-file
